kiln_cli/__init__.py
kiln_cli/accounts.py
kiln_cli/atom.py
kiln_cli/eth.py
kiln_cli/main.py
kiln_cli/matic.py
kiln_cli/sol.py
kiln_cli/xtz.py
kiln_connect/__init__.py
kiln_connect/accounts.py
kiln_connect/atom.py
kiln_connect/errors.py
kiln_connect/eth.py
kiln_connect/integrations.py
kiln_connect/kiln_connect.py
kiln_connect/matic.py
kiln_connect/openapi_client/__init__.py
kiln_connect/openapi_client/api/__init__.py
kiln_connect/openapi_client/api/accounts_api.py
kiln_connect/openapi_client/api/ada_api.py
kiln_connect/openapi_client/api/atom_api.py
kiln_connect/openapi_client/api/eth_api.py
kiln_connect/openapi_client/api/matic_api.py
kiln_connect/openapi_client/api/organizations_api.py
kiln_connect/openapi_client/api/sol_api.py
kiln_connect/openapi_client/api/xtz_api.py
kiln_connect/openapi_client/api_client.py
kiln_connect/openapi_client/api_response.py
kiln_connect/openapi_client/configuration.py
kiln_connect/openapi_client/exceptions.py
kiln_connect/openapi_client/models/__init__.py
kiln_connect/openapi_client/models/account.py
kiln_connect/openapi_client/models/account_payload.py
kiln_connect/openapi_client/models/ada_broadcast_tx_payload.py
kiln_connect/openapi_client/models/ada_craft_stake_tx_payload.py
kiln_connect/openapi_client/models/ada_craft_unstake_tx_payload.py
kiln_connect/openapi_client/models/ada_craft_withdraw_rewards_tx_payload.py
kiln_connect/openapi_client/models/ada_prepare_tx_payload.py
kiln_connect/openapi_client/models/ada_prepare_tx_payload_signed_messages_inner.py
kiln_connect/openapi_client/models/ada_signed_tx.py
kiln_connect/openapi_client/models/ada_unsigned_tx.py
kiln_connect/openapi_client/models/adatx_hash.py
kiln_connect/openapi_client/models/adatx_status.py
kiln_connect/openapi_client/models/atom_broadcast_tx_payload.py
kiln_connect/openapi_client/models/atom_craft_stake_tx_payload.py
kiln_connect/openapi_client/models/atom_craft_unstake_tx_payload.py
kiln_connect/openapi_client/models/atom_craft_withdraw_rewards_tx_payload.py
kiln_connect-1.0.0.dev8.dist-info/METADATA
kiln_connect-1.0.0.dev8.dist-info/WHEEL
kiln_connect-1.0.0.dev8.dist-info/entry_points.txt
kiln_connect-1.0.0.dev8.dist-info/RECORD
