Metadata-Version: 2.1
Name: kiln-connect
Version: 1.0.0.dev8
Summary: 
Home-page: https://kiln.fi/
Keywords: staking,blockchain
Author: s. rannou
Author-email: mxs@sbrk.org
Maintainer: s. rannou
Maintainer-email: mxs@sbrk.org
Requires-Python: >=3.9,<4.0
Classifier: Programming Language :: Python :: 3
Classifier: Programming Language :: Python :: 3.9
Classifier: Programming Language :: Python :: 3.10
Classifier: Programming Language :: Python :: 3.11
Requires-Dist: fireblocks-sdk (>=1.18.4,<2.0.0)
Requires-Dist: frozendict (>=2.3.4,<3.0.0)
Requires-Dist: pydantic (>=1.10.4,<2.0.0)
Requires-Dist: python-dateutil (>=2.8.2,<3.0.0)
Requires-Dist: pyyaml (>=6.0,<7.0)
Requires-Dist: requests (>=2.28.2,<3.0.0)
Requires-Dist: rich (>=13.3.1,<14.0.0)
Requires-Dist: ruff (>=0.0.256,<0.0.257)
Requires-Dist: typer (>=0.7.0,<0.8.0)
Project-URL: Repository, https://github.com/kilnfi/sdk-py
